truvari/__init__.py
truvari/__main__.py
truvari/anno.py
truvari/bench.py
truvari/collapse.py
truvari/comparisons.py
truvari/consistency.py
truvari/divide.py
truvari/make_ga4gh.py
truvari/matching.py
truvari/msatovcf.py
truvari/phab.py
truvari/refine.py
truvari/region_vcf_iter.py
truvari/segmentation.py
truvari/stratify.py
truvari/stratp_test.py
truvari/utils.py
truvari/variant_file.py
truvari/variant_params.py
truvari/variant_record.py
truvari/vcf2df.py
truvari/annotations/__init__.py
truvari/annotations/addid.py
truvari/annotations/af_calc.py
truvari/annotations/bpovl.py
truvari/annotations/chunks.py
truvari/annotations/density.py
truvari/annotations/dpcnt.py
truvari/annotations/gccontent.py
truvari/annotations/grm.py
truvari/annotations/grpaf.py
truvari/annotations/gtcnt.py
truvari/annotations/hompct.py
truvari/annotations/lcr.py
truvari/annotations/numneigh.py
truvari/annotations/remap.py
truvari/annotations/repmask.py
truvari/annotations/svinfo.py
truvari/annotations/trf.py
truvari-5.4.0.dist-info/licenses/LICENSE
truvari-5.4.0.dist-info/METADATA
truvari-5.4.0.dist-info/WHEEL
truvari-5.4.0.dist-info/entry_points.txt
truvari-5.4.0.dist-info/top_level.txt
truvari-5.4.0.dist-info/RECORD
