Metadata-Version: 2.4
Name: truvari
Version: 5.4.0
Summary: Structural variant comparison tool for VCFs
Author-email: ACEnglish <acenglish@gmail.com>
License: MIT
Project-URL: Homepage, https://github.com/ACEnglish/truvari
Project-URL: Documentation, https://truvari.readthedocs.io/en/latest/
Project-URL: Issues, https://github.com/ACEnglish/truvari/issues
Project-URL: Changelog, https://github.com/ACEnglish/truvari/wiki/Updates
Requires-Python: >=3.8
License-File: LICENSE
Requires-Dist: edlib>=1.3.9
Requires-Dist: intervaltree>=3.1
Requires-Dist: joblib>=1.2.0
Requires-Dist: numpy>=1.24.4
Requires-Dist: rich>=12.5.1
Requires-Dist: pandas>=1.5.3
Requires-Dist: psutil>=7.0.0
Requires-Dist: pyabpoa>=1.4.3
Requires-Dist: pysam>=0.22
Requires-Dist: pytabix>=0.1
Requires-Dist: pywfa>=0.5.1
Provides-Extra: bwa
Requires-Dist: bwapy>=0.1.4; extra == "bwa"
Dynamic: license-file
